Spruce_pprint-0.1.3-py2.7-nspkg.pth
spruce/pprint/_extensions.py
spruce/pprint/_pprinters.py
spruce/pprint/_misc.py
spruce/pprint/__init__.py
Spruce_pprint-0.1.3.dist-info/top_level.txt
Spruce_pprint-0.1.3.dist-info/RECORD
Spruce_pprint-0.1.3.dist-info/pydist.json
Spruce_pprint-0.1.3.dist-info/WHEEL
Spruce_pprint-0.1.3.dist-info/namespace_packages.txt
Spruce_pprint-0.1.3.dist-info/METADATA
Spruce_pprint-0.1.3.dist-info/entry_points.txt
Spruce_pprint-0.1.3.dist-info/DESCRIPTION.rst
