Metadata-Version: 2.0
Name: Spruce-pprint
Version: 0.1.3
Summary: String formatting
Home-page: UNKNOWN
Author: Ivan D Vasin
Author-email: nisavid@gmail.com
License: GNU LESSER GENERAL PUBLIC LICENSE
